MANIFEST.in
README.md
setup.py
gsc_libpythonpro.egg-info/PKG-INFO
gsc_libpythonpro.egg-info/SOURCES.txt
gsc_libpythonpro.egg-info/dependency_links.txt
gsc_libpythonpro.egg-info/not-zip-safe
gsc_libpythonpro.egg-info/requires.txt
gsc_libpythonpro.egg-info/top_level.txt
libpythonpro_gsc/__init__.py
libpythonpro_gsc/github_api.py