Metadata-Version: 2.1
Name: gsc-libpythonpro
Version: 0.2
Summary: Modulo para exemplificar a construcao de projetos Python no curso Pytools
Home-page: https://github.com/guisouco/libpythonpro_gsc
Author: Guilherme Colacio
Author-email: guilherme.souzacolacio@gmail.com
License: GNU AFFERO GENERAL PUBLIC LICENSE
Platform: UNKNOWN
Classifier: Development Status :: 2 - Pre-Alpha
Classifier: Environment :: Console
Classifier: Intended Audience :: Developers
Classifier: License :: OSI Approved :: GNU Affero General Public License v3 or later (AGPLv3+)
Classifier: Operating System :: OS Independent
Classifier: Programming Language :: Python
Classifier: Programming Language :: Python :: 3.9
Classifier: Framework :: Pytest
